multicluster_kubespawner/__init__.py
multicluster_kubespawner/infra.py
multicluster_kubespawner/kubectl.py
multicluster_kubespawner/spawner.py
jupyterhub_multicluster_kubespawner-0.2.dist-info/LICENSE
jupyterhub_multicluster_kubespawner-0.2.dist-info/METADATA
jupyterhub_multicluster_kubespawner-0.2.dist-info/WHEEL
jupyterhub_multicluster_kubespawner-0.2.dist-info/top_level.txt
jupyterhub_multicluster_kubespawner-0.2.dist-info/RECORD
