Metadata-Version: 2.1
Name: jupyterhub-multicluster-kubespawner
Version: 0.2
Summary: JupyterHub Spawner for spawning into multiple kubernetes clusters
Home-page: https://github.com/yuvipanda/jupyterhub-multicluster-kubespawner
Author: Yuvi Panda
Author-email: yuvipanda@gmail.com
License: 3-BSD
Project-URL: Source, https://github.com/yuvipanda/jupyterhub-multicluster-kubespawner
Project-URL: Tracker, https://github.com/yuvipanda/jupyterhub-multicluster-kubespawner/issues
Platform: UNKNOWN
Requires-Python: >=3.9
License-File: LICENSE
Requires-Dist: escapism
Requires-Dist: jupyterhub (>=1.5)
Requires-Dist: jinja2
Requires-Dist: ruamel.yaml
Requires-Dist: traitlets
